medsenger_api/__init__.py
medsenger_api/api_client.py
medsenger_api/certificates.py
medsenger_api/grpc_client.py
medsenger_api/rest_client.py
medsenger_api/utils.py
medsenger_api/protocol/__init__.py
medsenger_api/protocol/records_pb2.py
medsenger_api/protocol/records_pb2_grpc.py
medsenger_api-0.1.92.dist-info/licenses/LICENSE
medsenger_api-0.1.92.dist-info/METADATA
medsenger_api-0.1.92.dist-info/WHEEL
medsenger_api-0.1.92.dist-info/top_level.txt
medsenger_api-0.1.92.dist-info/RECORD
