Metadata-Version: 2.4
Name: medsenger_api
Version: 0.1.92
Summary: Python SDK for Medsenger.AI
Home-page: https://github.com/roctbb/medsenger_api
Author: Rostislav Borodin
Author-email: borodin@medsenger.ru
License: BSD 2-clause
Classifier: License :: OSI Approved :: BSD License
Classifier: Programming Language :: Python :: 3.7
License-File: LICENSE
Requires-Dist: requests
Requires-Dist: python-magic
Requires-Dist: grpcio
Requires-Dist: grpcio-tools
Requires-Dist: sentry-sdk
Dynamic: author
Dynamic: author-email
Dynamic: classifier
Dynamic: home-page
Dynamic: license
Dynamic: license-file
Dynamic: requires-dist
Dynamic: summary
